{
   "parents":{
      "DRIVE_BAY_TO_DRIVE_ASSOC":[
         {
            "parents":{
               "DRIVE_ENCLOSURE_TO_DRIVE_BAY_ASSOC":[
                  {
                     "parents":{
                        "ENCLOSURE_TO_BLADE":[
                           {
                              "parents":{

                              },
                              "resource":{
                                 "attributes":{
                                    "encgrp_uri":"/rest/enclosure-groups/bc41f38d-e8ce-4241-acd1-00b2d8c5d0fa",
                                    "fw_baseline_name":"",
                                    "reapply_config_state":"NotReapplyingConfiguration",
                                    "serial_number":"0000A66102",
                                    "uuid":"0000000000A66102",
                                    "state_reason":"",
                                    "model":"Synergy 12000 Frame",
                                    "enclosure_type_uri":"/rest/enclosure-types/SY12000",
                                    "refresh_state":"NotRefreshing",
                                    "part_number":"000000-010"
                                 },
                                 "status":"OK",
                                 "state":"Configured",
                                 "category":"enclosures",
                                 "applianceId":"c9ba5ca4-c1f8-48c7-9798-1e8b8897ef50",
                                 "eTag":"2018-07-23T19:34:24.315Z",
                                 "modified":"2018-07-23T19:34:24.315Z",
                                 "type":"IndexResourceV300",
                                 "name":"0000A66102",
                                 "created":"2018-04-10T19:45:55.872Z",
                                 "multiAttributes":{
                                    "interconnect_bay_number":[
                                       "1",
                                       "2",
                                       "3",
                                       "4",
                                       "5",
                                       "6"
                                    ],
                                    "fan_status":[
                                       "OK",
                                       "OK",
                                       "OK",
                                       "OK",
                                       "OK",
                                       "OK",
                                       "OK",
                                       "OK",
                                       "OK",
                                       "OK"
                                    ],
                                    "em_presence":[
                                       "Present",
                                       "Present"
                                    ],
                                    "power_supply_part_number":[
                                       "0000008710",
                                       "0000008710",
                                       "0000008710",
                                       "0000008710",
                                       "0000008710",
                                       "0000008710"
                                    ],
                                    "fan_part_number":[
                                       "0008568710",
                                       "0008568710",
                                       "0008568710",
                                       "0008568710",
                                       "0008568710",
                                       "0008568710",
                                       "0008568710",
                                       "0008568710",
                                       "0008568710",
                                       "0008568710"
                                    ],
                                    "em_role":[
                                       "Active",
                                       "Standby"
                                    ],
                                    "fan_bay_number":[
                                       "1",
                                       "2",
                                       "3",
                                       "4",
                                       "5",
                                       "6",
                                       "7",
                                       "8",
                                       "9",
                                       "10"
                                    ],
                                    "device_presence":[
                                       "Present",
                                       "Subsumed",
                                       "Present",
                                       "Present",
                                       "Present",
                                       "Present",
                                       "Present",
                                       "Present",
                                       "Subsumed",
                                       "Subsumed",
                                       "Present",
                                       "Subsumed"
                                    ],
                                    "interconnect_uri":[
                                       "/rest/sas-interconnects/2M220102SL",
                                       "/rest/interconnects/d777e2bb-f66b-4f3c-98ba-1953cfb0790c",
                                       "/rest/interconnects/9942a46b-417d-4da9-bda6-fdbcdbba4ffc",
                                       "/rest/sas-interconnects/2M220103SL",
                                       "/rest/interconnects/c3cc5d95-88ee-45c9-976f-c49eb61a8ead",
                                       "/rest/interconnects/35db51bf-457d-4f16-a71d-cca928e43885"
                                    ],
                                    "em_ip_address":[
                                       "fe80::2:0:9:3%eth2",
                                       "fe80::2:0:9:4%eth2"
                                    ],
                                    "em_fw_version":[
                                       "2.00.00",
                                       "2.00.00"
                                    ],
                                    "em_bay_number":[
                                       "1",
                                       "2"
                                    ],
                                    "device_uri":[
                                       "/rest/drive-enclosures/SN123101",
                                       "",
                                       "/rest/server-hardware/30373737-3237-4D32-3230-313530384752",
                                       "/rest/server-hardware/30373737-3237-4D32-3230-313531324752",
                                       "/rest/server-hardware/30303437-3034-4D32-3230-313131324752",
                                       "/rest/server-hardware/33343538-3136-4332-3230-313530364752",
                                       "/rest/server-hardware/30303437-3034-4D32-3230-313131384752",
                                       "/rest/server-hardware/30303437-3034-4D32-3230-313132314752",
                                       "",
                                       "",
                                       "/rest/server-hardware/33343538-3435-4A32-3230-313130344752",
                                       ""
                                    ],
                                    "power_supply_bay_number":[
                                       "1",
                                       "2",
                                       "3",
                                       "4",
                                       "5",
                                       "6"
                                    ],
                                    "power_supply_status":[
                                       "OK",
                                       "OK",
                                       "OK",
                                       "OK",
                                       "OK",
                                       "OK"
                                    ],
                                    "device_bay_number":[
                                       "1",
                                       "2",
                                       "3",
                                       "4",
                                       "5",
                                       "6",
                                       "7",
                                       "8",
                                       "9",
                                       "10",
                                       "11",
                                       "12"
                                    ]
                                 },
                                 "description":"",
                                 "ownerId":"perm",
                                 "uri":"/rest/enclosures/0000000000A66102",
                                 "scopeUris":""
                              },
                              "children":{

                              }
                           }
                        ],
                        "SASINTERCONNECT_TO_DRIVE_ENCLOSURE":[
                           {
                              "parents":{

                              },
                              "resource":{
                                 "attributes":{
                                    "refreshState":"NotRefreshing",
                                    "uidState":"Off",
                                    "fwbaseline_version":"1.1.5.0",
                                    "model":"Synergy 12Gb SAS Connection Module",
                                    "location":"[Enclosure=/rest/enclosures/0000000000A66102,Bay=1]",
                                    "serial_number":"2M220102SL",
                                    "part_number":"755985-B21"
                                 },
                                 "status":"OK",
                                 "state":"Configured",
                                 "category":"sas-interconnects",
                                 "applianceId":"c9ba5ca4-c1f8-48c7-9798-1e8b8897ef50",
                                 "eTag":"2018-07-23T19:14:53.465Z",
                                 "modified":"2018-07-23T19:14:53.465Z",
                                 "type":"IndexResourceV300",
                                 "name":"0000A66102, interconnect 1",
                                 "created":"2018-04-10T19:46:34.152Z",
                                 "multiAttributes":{
                                    "hostname":[
                                       "fe80::2:0:8:3%eth2"
                                    ]
                                 },
                                 "description":"",
                                 "ownerId":"dfrm",
                                 "uri":"/rest/sas-interconnects/2M220102SL",
                                 "scopeUris":""
                              },
                              "children":{

                              }
                           },
                           {
                              "parents":{

                              },
                              "resource":{
                                 "attributes":{
                                    "refreshState":"NotRefreshing",
                                    "uidState":"Off",
                                    "fwbaseline_version":"1.1.5.0",
                                    "model":"Synergy 12Gb SAS Connection Module",
                                    "location":"[Enclosure=/rest/enclosures/0000000000A66102,Bay=4]",
                                    "serial_number":"2M220103SL",
                                    "part_number":"755985-B21"
                                 },
                                 "status":"OK",
                                 "state":"Configured",
                                 "category":"sas-interconnects",
                                 "applianceId":"c9ba5ca4-c1f8-48c7-9798-1e8b8897ef50",
                                 "eTag":"2018-07-23T19:14:53.082Z",
                                 "modified":"2018-07-23T19:14:53.082Z",
                                 "type":"IndexResourceV300",
                                 "name":"0000A66102, interconnect 4",
                                 "created":"2018-04-10T19:47:16.057Z",
                                 "multiAttributes":{
                                    "hostname":[
                                       "fe80::2:0:8:4%eth2"
                                    ]
                                 },
                                 "description":"",
                                 "ownerId":"dfrm",
                                 "uri":"/rest/sas-interconnects/2M220103SL",
                                 "scopeUris":""
                              },
                              "children":{

                              }
                           }
                        ],
                        "DEVICE_BAY_TO_SERVER_HARDWARE":[
                           {
                              "parents":{

                              },
                              "resource":{
                                 "attributes":{
                                    "devicePresence":"Present",
                                    "coveredByDevice":"/rest/drive-enclosures/SN123101"
                                 },
                                 "status":"",
                                 "state":"",
                                 "category":"device-bays",
                                 "applianceId":"c9ba5ca4-c1f8-48c7-9798-1e8b8897ef50",
                                 "eTag":"2018-07-23T19:34:24.521Z",
                                 "modified":"2018-07-23T19:34:24.521Z",
                                 "type":"IndexResourceV300",
                                 "name":"0000A66102, bay 1",
                                 "created":"2018-04-10T19:45:56.302Z",
                                 "multiAttributes":{

                                 },
                                 "description":"",
                                 "ownerId":"perm",
                                 "uri":"/rest/enclosures/0000000000A66102/device-bays/1",
                                 "scopeUris":""
                              },
                              "children":{

                              }
                           }
                        ]
                     },
                     "resource":{
                        "attributes":{
                           "IOAdapter2Model":"HPE Synergy 12Gb SAS Storage IO Adapter",
                           "model_short":"SY D3940",
                           "IOAdapter1ProductName":"",
                           "IOAdapter2Type":"HpSmartStorageIOModule.1.0.0",
                           "IOAdapter2ProductName":"",
                           "IOAdapter2Name":"I/O adapter 2",
                           "refreshState":"NotRefreshing",
                           "powerState":"On",
                           "bay":"1",
                           "part_number":"755984-B21",
                           "IOAdapter1Model":"HPE Synergy 12Gb SAS Storage IO Adapter",
                           "name":"0000A66102, bay 1",
                           "uuid":"SN123101",
                           "IOAdapter2Id":"a80e0bb8-441b-41ca-bfb5-d8d6d3ea2df9",
                           "IOAdapter2Location":"2",
                           "IOAdapter1Type":"HpSmartStorageIOModule.1.0.0",
                           "IOAdapter1Id":"23e87cca-5bed-4182-91ed-ad2c51e56312",
                           "serial_number":"SN123101",
                           "IOAdapter1Firmware":"2.07",
                           "IOAdapter1Name":"I/O adapter 1",
                           "uidState":"Off",
                           "fwbaseline_version":"0.18",
                           "model":"Synergy D3940 Storage Module",
                           "IOAdapter1Location":"1",
                           "IOAdapter2Firmware":"2.07"
                        },
                        "status":"OK",
                        "state":"Configured",
                        "category":"drive-enclosures",
                        "applianceId":"c9ba5ca4-c1f8-48c7-9798-1e8b8897ef50",
                        "eTag":"2018-07-23T19:28:13.937Z",
                        "modified":"2018-07-23T19:28:13.937Z",
                        "type":"IndexResourceV300",
                        "name":"0000A66102, bay 1",
                        "created":"2018-04-10T19:48:50.956Z",
                        "multiAttributes":{

                        },
                        "description":"",
                        "ownerId":"dfrm",
                        "uri":"/rest/drive-enclosures/SN123101",
                        "scopeUris":""
                     },
                     "children":{

                     }
                  }
               ]
            },
            "resource":{
               "attributes":{
                  "model":"SAS 3276",
                  "location":"40"
               },
               "status":"",
               "state":"",
               "category":"drive-bays",
               "applianceId":"c9ba5ca4-c1f8-48c7-9798-1e8b8897ef50",
               "eTag":"2018-07-20T16:21:15.170Z",
               "modified":"2018-07-20T16:21:15.170Z",
               "type":"IndexResourceV300",
               "name":"Drive Bay 40",
               "created":"2018-04-10T19:51:48.269Z",
               "multiAttributes":{

               },
               "description":"",
               "ownerId":"dfrm",
               "uri":"/rest/drive-enclosures/SN123101/drive-bays/44378170-cbef-43bb-aef4-4e3c98989ae5",
               "scopeUris":""
            },
            "children":{

            }
         }
      ]
   },
   "resource":{
      "attributes":{
         "interfaceType":"SAS",
         "driveEnclosureUri":"/rest/drive-enclosures/SN123101",
         "isSanitizable":"Supported",
         "capacityInGB":"3276",
         "available":"yes",
         "isPredictiveFailDrive":"no",
         "mediaType":"SSD"
      },
      "status":"OK",
      "state":"",
      "category":"drives",
      "applianceId":"c9ba5ca4-c1f8-48c7-9798-1e8b8897ef50",
      "eTag":"2018-07-20T16:21:15.124Z",
      "modified":"2018-07-20T16:21:15.124Z",
      "type":"IndexResourceV300",
      "name":"Drive 40",
      "created":"2018-04-10T19:51:48.269Z",
      "multiAttributes":{

      },
      "description":"",
      "ownerId":"dfrm",
      "uri":"/rest/drives/eb03e945-938e-4ee7-a1cf-eb18b0fda637",
      "scopeUris":""
   },
   "children":{

   }
}